odoo/addons/sale_weight/README.rst
odoo/addons/sale_weight/__init__.py
odoo/addons/sale_weight/__manifest__.py
odoo/addons/sale_weight/i18n/es.po
odoo/addons/sale_weight/models/__init__.py
odoo/addons/sale_weight/models/sale_order.py
odoo/addons/sale_weight/models/sale_order_line.py
odoo/addons/sale_weight/static/description/icon.png
odoo/addons/sale_weight/views/sale_order.xml
odoo13_addon_sale_weight-13.0.1.0.1.dev1.dist-info/METADATA
odoo13_addon_sale_weight-13.0.1.0.1.dev1.dist-info/WHEEL
odoo13_addon_sale_weight-13.0.1.0.1.dev1.dist-info/top_level.txt
odoo13_addon_sale_weight-13.0.1.0.1.dev1.dist-info/RECORD
