Metadata-Version: 2.1
Name: odoo13-addon-sale_weight
Version: 13.0.1.0.1.dev1
Summary: Show weight in sale orders and sale order lines
Home-page: https://www.sygel.es
Author: Sygel
License: AGPL-3
Classifier: Programming Language :: Python
Classifier: Framework :: Odoo
Classifier: Framework :: Odoo :: 13.0
Classifier: License :: OSI Approved :: GNU Affero General Public License v3
Requires-Python: >=3.5
Requires-Dist: odoo<13.1dev,>=13.0a
